Workbook

Sheet How to use
A1: Annual report reader
A2: The GM's Ledger course template. The example figures are Invacare Corporation's, from its published Form 10-K filings (US$ millions): replace them with any company's.
A4: What it's for
A5: Turn any company's annual report into ratios and warning signs in ten minutes: a competitor, a customer, a supplier, or your own audited accounts (Module 21).
A7: How to use it
A8: 1. Type the company name and the report's currency and unit on the Inputs sheet.
A9: 2. Copy up to four years of figures from the statements into the yellow cells. Start with the oldest year in column C.
A10: 3. Leave optional lines blank if the report doesn't give them.
A11: 4. Open Ratios and flags. Read each red warning sign, then find the note or statement that explains it.
A12: 5. Write three sentences: how the company is doing, its biggest risk, and what you'd watch next year.
A14: Colour legend
A15: Blue text on yellow: an input. Type your own figures here.
... A17: Green text: a figure brought in from another sheet.

Sheet Inputs
A1: Annual report reader: inputs
A2: Type figures straight from the report, in the report's own currency and unit. Example: Invacare Corporation, US$ millions, from its Form 10-K filings 2019 to 2022.
A3: Company | C3: Invacare Corporation
A4: Currency and unit | C4: US$ millions
A6: Line | B6: Where to find it | C6: Year 1 | D6: Year 2 | E6: Year 3 | F6: Year 4
A7: Year | C7: 2019 | D7: 2020 | E7: 2021 | F7: 2022
A8: Net sales | B8: Income statement | C8: 928 | D8: 850.7 | E8: 872.5 | F8: 741.7
A9: Gross profit | B9: Income statement | C9: 262.1 | D9: 245.3 | E9: 239.1 | F9: 175.4
A10: Operating profit (EBIT) | B10: Income statement | C10: -10.4 | D10: 11.3 | E10: -24.2 | F10: -80.5
A11: Depreciation and amortisation (optional) | B11: Cash flow statement, first lines
A12: Net profit (loss) | B12: Income statement | C12: -53.3 | D12: -28.3 | E12: -45.6 | F12: -101.1
A13: One-off gains (+) or costs (-) inside operating profit (optional) | B13: Income statement and notes | C13: -0.6 | D13: 9.8 | E13: -28.6 | F13: -3.3
A14: Net cash from operating activities | B14: Cash flow statement | C14: 2.7 | D14: 21.9 | E14: -14.3 | F14: -55.3
A15: Capital spending (type as a positive number) | B15: Cash flow statement, investing | C15: 10.9 | D15: 22.3 | E15: 17.7 | F15: 3.8
A16: Cash and cash equivalents | B16: Balance sheet | C16: 80.1 | D16: 105.3 | E16: 83.7 | F16: 58.8
A17: Trade receivables | B17: Balance sheet | C17: 116.7 | D17: 108.6 | E17: 117.1 | F17: 88
A18: Inventories | B18: Balance sheet | C18: 120.5 | D18: 115.5 | E18: 144.3 | F18: 112.6
A19: Trade payables (optional) | B19: Balance sheet
A20: Total borrowings | B20: Balance sheet or debt note | C20: 219.5 | D20: 245.1 | E20: 308.1 | F20: 354.2
A21: Total equity | B21: Balance sheet | C21: 308.5 | D21: 333.8 | E21: 218.5 | F21: 81.1
A22: Total assets (optional) | B22: Balance sheet
A23: Goodwill | B23: Balance sheet or goodwill note | C23: 373.4 | D23: 402.5 | E23: 355.9 | F23: 326.3
A25: Invacare notes: one-off items are impairments (2019, 2021, 2022) and the gain on selling Dynamic Controls (2020). Restructuring costs came every year, so they are left in. Borrowings exclude finance leases, as in the debt note. Source: Invacare Form 10-K filings on SEC EDGAR.
A26: Leave optional lines blank if the report doesn't give them: the ratios that need them will show n/a.

Sheet Ratios and flags
A1: Ratios and warning signs
A2: ="Company: "&Inputs!C3&" · "&Inputs!C4 -> Company: Invacare Corporation · US$ millions
A4: Ratio | B4: What it tells you | C4: Year 1 | D4: Year 2 | E4: Year 3 | F4: Year 4
A5: Year | C5: =Inputs!C7 -> 2019 | D5: =Inputs!D7 -> 2020 | E5: =Inputs!E7 -> 2021 | F5: =Inputs!F7 -> 2022
A6: Sales growth | B6: Is the business growing? | C6: n/a | D6: =IF(OR(Inputs!C8="",Inputs!C8=0),"n/a",Inputs!D8/Inputs!C8-1) -> -0.083297414 | E6: =IF(OR(Inputs!D8="",Inputs!D8=0),"n/a",Inputs!E8/Inputs!D8-1) -> 0.025625955 | F6: =IF(OR(Inputs!E8="",Inputs!E8=0),"n/a",Inputs!F8/Inputs!E8-1) -> -0.14991404
A7: Gross margin | B7: Pricing and factory efficiency | C7: =IF(Inputs!C8=0,"n/a",Inputs!C9/Inputs!C8) -> 0.28243534 | D7: =IF(Inputs!D8=0,"n/a",Inputs!D9/Inputs!D8) -> 0.28835077 | E7: =IF(Inputs!E8=0,"n/a",Inputs!E9/Inputs!E8) -> 0.27404011 | F7: =IF(Inputs!F8=0,"n/a",Inputs!F9/Inputs!F8) -> 0.23648375
A8: Operating margin | B8: Profit from operations per sales dollar | C8: =IF(Inputs!C8=0,"n/a",Inputs!C10/Inputs!C8) -> -0.011206897 | D8: =IF(Inputs!D8=0,"n/a",Inputs!D10/Inputs!D8) -> 0.013283179 | E8: =IF(Inputs!E8=0,"n/a",Inputs!E10/Inputs!E8) -> -0.02773639 | F8: =IF(Inputs!F8=0,"n/a",Inputs!F10/Inputs!F8) -> -0.10853445
A9: Underlying operating margin (without one-offs) | B9: What the ongoing business earned | C9: =IF(Inputs!C8=0,"n/a",(Inputs!C10-N(Inputs!C13))/Inputs!C8) -> -0.010560345 | D9: =IF(Inputs!D8=0,"n/a",(Inputs!D10-N(Inputs!D13))/Inputs!D8) -> 0.0017632538 | E9: =IF(Inputs!E8=0,"n/a",(Inputs!E10-N(Inputs!E13))/Inputs!E8) -> 0.0050429799 | F9: =IF(Inputs!F8=0,"n/a",(Inputs!F10-N(Inputs!F13))/Inputs!F8) -> -0.10408521
A10: EBITDA | B10: Needs depreciation and amortisation | C10: =IF(Inputs!C11="","n/a",Inputs!C10+Inputs!C11) -> n/a | D10: =IF(Inputs!D11="","n/a",Inputs!D10+Inputs!D11) -> n/a | E10: =IF(Inputs!E11="","n/a",Inputs!E10+Inputs!E11) -> n/a | F10: =IF(Inputs!F11="","n/a",Inputs!F10+Inputs!F11) -> n/a
A11: Net margin | B11: What owners keep | C11: =IF(Inputs!C8=0,"n/a",Inputs!C12/Inputs!C8) -> -0.057435345 | D11: =IF(Inputs!D8=0,"n/a",Inputs!D12/Inputs!D8) -> -0.033266722 | E11: =IF(Inputs!E8=0,"n/a",Inputs!E12/Inputs!E8) -> -0.05226361 | F11: =IF(Inputs!F8=0,"n/a",Inputs!F12/Inputs!F8) -> -0.13630848
A12: Cash conversion (operating cash flow ÷ EBITDA) | B12: Is profit turning into cash? | C12: =IF(OR(Inputs!C11="",Inputs!C10+Inputs!C11<=0),"n/a",Inputs!C14/(Inputs!C10+Inputs!C11)) -> n/a | D12: =IF(OR(Inputs!D11="",Inputs!D10+Inputs!D11<=0),"n/a",Inputs!D14/(Inputs!D10+Inputs!D11)) -> n/a | E12: =IF(OR(Inputs!E11="",Inputs!E10+Inputs!E11<=0),"n/a",Inputs!E14/(Inputs!E10+Inputs!E11)) -> n/a | F12: =IF(OR(Inputs!F11="",Inputs!F10+Inputs!F11<=0),"n/a",Inputs!F14/(Inputs!F10+Inputs!F11)) -> n/a
A13: Free cash flow (operating cash flow − capital spending) | B13: Can the business pay its own way? | C13: =Inputs!C14-Inputs!C15 -> -8.2 | D13: =Inputs!D14-Inputs!D15 -> -0.4 | E13: =Inputs!E14-Inputs!E15 -> -32 | F13: =Inputs!F14-Inputs!F15 -> -59.1
A14: Free cash flow % of sales | C14: =IF(Inputs!C8=0,"n/a",(Inputs!C14-Inputs!C15)/Inputs!C8) -> -0.0088362069 | D14: =IF(Inputs!D8=0,"n/a",(Inputs!D14-Inputs!D15)/Inputs!D8) -> -0.00047020101 | E14: =IF(Inputs!E8=0,"n/a",(Inputs!E14-Inputs!E15)/Inputs!E8) -> -0.036676218 | F14: =IF(Inputs!F8=0,"n/a",(Inputs!F14-Inputs!F15)/Inputs!F8) -> -0.079681812
A15: Days sales outstanding | B15: How fast customers pay | C15: =IF(Inputs!C8=0,"n/a",Inputs!C17/Inputs!C8*365) -> 45.900323 | D15: =IF(Inputs!D8=0,"n/a",Inputs!D17/Inputs!D8*365) -> 46.595745 | E15: =IF(Inputs!E8=0,"n/a",Inputs!E17/Inputs!E8*365) -> 48.987393 | F15: =IF(Inputs!F8=0,"n/a",Inputs!F17/Inputs!F8*365) -> 43.305919
A16: Inventory days | B16: How long stock sits | C16: =IF(Inputs!C8-Inputs!C9<=0,"n/a",Inputs!C18/(Inputs!C8-Inputs!C9)*365) -> 66.049707 | D16: =IF(Inputs!D8-Inputs!D9<=0,"n/a",Inputs!D18/(Inputs!D8-Inputs!D9)*365) -> 69.635778 | E16: =IF(Inputs!E8-Inputs!E9<=0,"n/a",Inputs!E18/(Inputs!E8-Inputs!E9)*365) -> 83.153615 | F16: =IF(Inputs!F8-Inputs!F9<=0,"n/a",Inputs!F18/(Inputs!F8-Inputs!F9)*365) -> 72.574607
A17: Payable days | B17: How long it takes to pay suppliers | C17: =IF(OR(Inputs!C19="",Inputs!C8-Inputs!C9<=0),"n/a",Inputs!C19/(Inputs!C8-Inputs!C9)*365) -> n/a | D17: =IF(OR(Inputs!D19="",Inputs!D8-Inputs!D9<=0),"n/a",Inputs!D19/(Inputs!D8-Inputs!D9)*365) -> n/a | E17: =IF(OR(Inputs!E19="",Inputs!E8-Inputs!E9<=0),"n/a",Inputs!E19/(Inputs!E8-Inputs!E9)*365) -> n/a | F17: =IF(OR(Inputs!F19="",Inputs!F8-Inputs!F9<=0),"n/a",Inputs!F19/(Inputs!F8-Inputs!F9)*365) -> n/a
A18: Net debt (borrowings − cash) | C18: =Inputs!C20-Inputs!C16 -> 139.4 | D18: =Inputs!D20-Inputs!D16 -> 139.8 | E18: =Inputs!E20-Inputs!E16 -> 224.4 | F18: =Inputs!F20-Inputs!F16 -> 295.4
A19: Net debt ÷ EBITDA | B19: Years of EBITDA to repay debt | C19: =IF(OR(Inputs!C11="",Inputs!C10+Inputs!C11<=0),"n/a",(Inputs!C20-Inputs!C16)/(Inputs!C10+Inputs!C11)) -> n/a | D19: =IF(OR(Inputs!D11="",Inputs!D10+Inputs!D11<=0),"n/a",(Inputs!D20-Inputs!D16)/(Inputs!D10+Inputs!D11)) -> n/a | E19: =IF(OR(Inputs!E11="",Inputs!E10+Inputs!E11<=0),"n/a",(Inputs!E20-Inputs!E16)/(Inputs!E10+Inputs!E11)) -> n/a | F19: =IF(OR(Inputs!F11="",Inputs!F10+Inputs!F11<=0),"n/a",(Inputs!F20-Inputs!F16)/(Inputs!F10+Inputs!F11)) -> n/a
A20: Debt ÷ equity | B20: Lenders' money vs owners' money | C20: =IF(Inputs!C21<=0,"n/a",Inputs!C20/Inputs!C21) -> 0.71150729 | D20: =IF(Inputs!D21<=0,"n/a",Inputs!D20/Inputs!D21) -> 0.73427202 | E20: =IF(Inputs!E21<=0,"n/a",Inputs!E20/Inputs!E21) -> 1.4100686 | F20: =IF(Inputs!F21<=0,"n/a",Inputs!F20/Inputs!F21) -> 4.3674476
A21: Goodwill ÷ equity | B21: Could a write-down wipe out equity? | C21: =IF(Inputs!C21<=0,"n/a",Inputs!C23/Inputs!C21) -> 1.2103728 | D21: =IF(Inputs!D21<=0,"n/a",Inputs!D23/Inputs!D21) -> 1.2058119 | E21: =IF(Inputs!E21<=0,"n/a",Inputs!E23/Inputs!E21) -> 1.628833 | F21: =IF(Inputs!F21<=0,"n/a",Inputs!F23/Inputs!F21) -> 4.0234279
A22: Goodwill ÷ total assets | B22: Needs total assets | C22: =IF(OR(Inputs!C22="",Inputs!C22=0),"n/a",Inputs!C23/Inputs!C22) -> n/a | D22: =IF(OR(Inputs!D22="",Inputs!D22=0),"n/a",Inputs!D23/Inputs!D22) -> n/a | E22: =IF(OR(Inputs!E22="",Inputs!E22=0),"n/a",Inputs!E23/Inputs!E22) -> n/a | F22: =IF(OR(Inputs!F22="",Inputs!F22=0),"n/a",Inputs!F23/Inputs!F22) -> n/a
A24: Warning signs (Module 21)
A25: Warning sign | B25: Why it matters | C25: Year 1 | D25: Year 2 | E25: Year 3 | F25: Year 4
A26: Free cash flow negative | B26: The business is spending more than it generates | C26: =IF(Inputs!C14-Inputs!C15<0,"Yes","-") -> Yes | D26: =IF(Inputs!D14-Inputs!D15<0,"Yes","-") -> Yes | E26: =IF(Inputs!E14-Inputs!E15<0,"Yes","-") -> Yes | F26: =IF(Inputs!F14-Inputs!F15<0,"Yes","-") -> Yes
A27: Operating cash flow negative | B27: Day-to-day operations use cash | C27: =IF(Inputs!C14<0,"Yes","-") -> - | D27: =IF(Inputs!D14<0,"Yes","-") -> - | E27: =IF(Inputs!E14<0,"Yes","-") -> Yes | F27: =IF(Inputs!F14<0,"Yes","-") -> Yes
A28: Receivables grew faster than sales | B28: Customers paying slower, or sales quality falling | C28: - | D28: =IF(OR(Inputs!C17="",Inputs!C17=0,Inputs!C8=0),"-",IF(Inputs!D17/Inputs!C17>Inputs!D8/Inputs!C8+0.02,"Yes","-")) -> - | E28: =IF(OR(Inputs!D17="",Inputs!D17=0,Inputs!D8=0),"-",IF(Inputs!E17/Inputs!D17>Inputs!E8/Inputs!D8+0.02,"Yes","-")) -> Yes | F28: =IF(OR(Inputs!E17="",Inputs!E17=0,Inputs!E8=0),"-",IF(Inputs!F17/Inputs!E17>Inputs!F8/Inputs!E8+0.02,"Yes","-")) -> -
A29: Inventory grew faster than sales | B29: Cash tied up in stock; possible slow-moving stock | C29: - | D29: =IF(OR(Inputs!C18="",Inputs!C18=0,Inputs!C8=0),"-",IF(Inputs!D18/Inputs!C18>Inputs!D8/Inputs!C8+0.02,"Yes","-")) -> Yes | E29: =IF(OR(Inputs!D18="",Inputs!D18=0,Inputs!D8=0),"-",IF(Inputs!E18/Inputs!D18>Inputs!E8/Inputs!D8+0.02,"Yes","-")) -> Yes | F29: =IF(OR(Inputs!E18="",Inputs!E18=0,Inputs!E8=0),"-",IF(Inputs!F18/Inputs!E18>Inputs!F8/Inputs!E8+0.02,"Yes","-")) -> -
A30: Gross margin fell more than 1 point | B30: Pricing or cost pressure | C30: - | D30: =IF(OR(Inputs!D8=0,Inputs!C8=0),"-",IF(Inputs!D9/Inputs!D8<Inputs!C9/Inputs!C8-0.01,"Yes","-")) -> - | E30: =IF(OR(Inputs!E8=0,Inputs!D8=0),"-",IF(Inputs!E9/Inputs!E8<Inputs!D9/Inputs!D8-0.01,"Yes","-")) -> Yes | F30: =IF(OR(Inputs!F8=0,Inputs!E8=0),"-",IF(Inputs!F9/Inputs!F8<Inputs!E9/Inputs!E8-0.01,"Yes","-")) -> Yes
A31: Net debt rose | B31: More reliance on lenders | C31: - | D31: =IF((Inputs!D20-Inputs!D16)>(Inputs!C20-Inputs!C16)+0.005*ABS(Inputs!C20),"Yes","-") -> - | E31: =IF((Inputs!E20-Inputs!E16)>(Inputs!D20-Inputs!D16)+0.005*ABS(Inputs!D20),"Yes","-") -> Yes | F31: =IF((Inputs!F20-Inputs!F16)>(Inputs!E20-Inputs!E16)+0.005*ABS(Inputs!E20),"Yes","-") -> Yes
A32: Equity fell by more than the loss | B32: Other losses going straight to equity: read the statement of changes in equity | C32: - | D32: =IF((Inputs!C21-Inputs!D21)-MAX(0,-Inputs!D12)>0.02*ABS(Inputs!C21),"Yes","-") -> - | E32: =IF((Inputs!D21-Inputs!E21)-MAX(0,-Inputs!E12)>0.02*ABS(Inputs!D21),"Yes","-") -> Yes | F32: =IF((Inputs!E21-Inputs!F21)-MAX(0,-Inputs!F12)>0.02*ABS(Inputs!E21),"Yes","-") -> Yes
A33: Goodwill larger than equity | B33: A write-down could wipe out the owners' cushion | C33: =IF(Inputs!C23>Inputs!C21,"Yes","-") -> Yes | D33: =IF(Inputs!D23>Inputs!D21,"Yes","-") -> Yes | E33: =IF(Inputs!E23>Inputs!E21,"Yes","-") -> Yes | F33: =IF(Inputs!F23>Inputs!F21,"Yes","-") -> Yes
A34: One-offs over half of operating profit | B34: Headline profit not representative | C34: =IF(Inputs!C13="","-",IF(ABS(Inputs!C13)>0.5*ABS(Inputs!C10),"Yes","-")) -> - | D34: =IF(Inputs!D13="","-",IF(ABS(Inputs!D13)>0.5*ABS(Inputs!D10),"Yes","-")) -> Yes | E34: =IF(Inputs!E13="","-",IF(ABS(Inputs!E13)>0.5*ABS(Inputs!E10),"Yes","-")) -> Yes | F34: =IF(Inputs!F13="","-",IF(ABS(Inputs!F13)>0.5*ABS(Inputs!F10),"Yes","-")) -> -
A35: Warning signs this year | C35: =COUNTIF(C26:C34,"Yes") -> 2 | D35: =COUNTIF(D26:D34,"Yes") -> 4 | E35: =COUNTIF(E26:E34,"Yes") -> 9 | F35: =COUNTIF(F26:F34,"Yes") -> 6
A37: Signs are prompts to read further, not verdicts. Check each one against the notes and the cash flow statement.
