Workbook

Sheet How to use
A1: Budget builder
A2: The GM's Ledger course template. Example figures are for BraceWorks Medical, a fictional company: replace them with your own.
A4: What it's for
A5: Build next year's budget in the right order: sales, materials, labour, overheads, then profit and cash (Module 15).
A7: How to use it
A8: 1. On the Assumptions sheet, enter last year's units, prices and costs for each product, and your growth, price and inflation assumptions.
A9: 2. Enter wages, overheads, selling costs, interest, tax rate, capex and loan repayments.
A10: 3. Set the monthly phasing so it reflects your seasons. It must total 100%.
A11: 4. Read the Budget P&L for monthly profit, contribution margin and break-even, then the Cash summary for whether you need extra funding.
A12: 5. Save a copy as the approved budget. Use a separate copy for monthly forecasts.
A14: Colour legend
A15: Blue text on yellow: an input. Type your own figures here.
... A19: Simplifications: production wages, overheads and selling costs are treated as fixed and spread evenly; materials, freight and commission move with sales. Tax is a simple rate on profit.

Sheet Assumptions
A1: Budget assumptions
A2: US dollars. Change the yellow cells; the budget P&L and cash summary update.
A4: Product | B4: Units last year | C4: Volume growth | D4: Price last year | E4: Price increase | F4: Material cost per unit last year | G4: Material inflation | H4: Budget units | I4: Budget price | J4: Budget material per unit | K4: Budget revenue | L4: Budget materials
A5: Mattresses | B5: 2800 | C5: 0.05 | D5: 180 | E5: 0.03 | F5: 95 | G5: 0.04 | H5: =B5*(1+C5) -> 2940 | I5: =D5*(1+E5) -> 185.4 | J5: =F5*(1+G5) -> 98.8 | K5: =H5*I5 -> 545076 | L5: =H5*J5 -> 290472
A6: Slings | B6: 7200 | C6: 0.05 | D6: 45 | E6: 0.03 | F6: 18 | G6: 0.04 | H6: =B6*(1+C6) -> 7560 | I6: =D6*(1+E6) -> 46.35 | J6: =F6*(1+G6) -> 18.72 | K6: =H6*I6 -> 350406 | L6: =H6*J6 -> 141523.2
A7: Braces | B7: 13000 | C7: 0.05 | D7: 28 | E7: 0.03 | F7: 11.8 | G7: 0.04 | H7: =B7*(1+C7) -> 13650 | I7: =D7*(1+E7) -> 28.84 | J7: =F7*(1+G7) -> 12.272 | K7: =H7*I7 -> 393666 | L7: =H7*J7 -> 167512.8
A8: Total | K8: =SUM(K5:K7) -> 1289148 | L8: =SUM(L5:L7) -> 599508
A10: Other assumptions
A11: Production wages last year | B11: 152000 | C11: Direct labour from last year's P&L
A12: Wage increase | B12: 0.06
A13: Extra production staff | B13: 0
A14: Cost of one extra production employee (a year) | B14: 4000 | C14: Including benefits
A15: Factory overhead last year (excluding depreciation) | B15: 118000
A16: Depreciation for the year | B16: 45500 | C16: Existing assets plus new equipment
A17: Overhead inflation | B17: 0.04
A18: Selling and admin costs last year (excluding freight and commission) | B18: 174000
A19: Selling and admin inflation | B19: 0.04
A20: Freight and export costs, % of sales | B20: 0.04
A21: Sales commission, % of sales | B21: 0.02
A22: Interest for the year | B22: 20000
A23: Tax rate | B23: 0.25 | C23: Example rate; see Module 19 for your country
A24: Equipment purchases (capex) | B24: 60000
A25: Loan repayments | B25: 20000
A26: Receivable days (DSO) | B26: 65 | C26: Target
A27: Inventory days | B27: 95 | C27: Target
A28: Payable days | B28: 63
A29: Opening receivables | B29: 230000 | C29: From the balance sheet
A30: Opening inventory | B30: 250000
A31: Opening payables | B31: 95000
A32: Opening cash | B32: 42000
A34: Monthly sales phasing (must total 100%)
B35: Jan | C35: Feb | D35: Mar | E35: Apr | F35: May | G35: Jun | H35: Jul | I35: Aug | J35: Sep | K35: Oct | L35: Nov | M35: Dec | N35: Total
A36: Share of the year's sales | B36: 0.065 | C36: 0.07 | D36: 0.085 | E36: 0.08 | F36: 0.0817 | G36: 0.0867 | H36: 0.0733 | I36: 0.0767 | J36: 0.0933 | K36: 0.09 | L36: 0.1033 | M36: 0.095 | N36: =SUM(B36:M36) -> 1
N37: =IF(ABS(N36-1)<0.0005,"OK","Must total 100%") -> OK

Sheet Budget P&L
A1: Budget income statement by month
A2: US dollars. All formulas: change the Assumptions sheet, not this one.
A4: US dollars | B4: Jan | C4: Feb | D4: Mar | E4: Apr | F4: May | G4: Jun | H4: Jul | I4: Aug | J4: Sep | K4: Oct | L4: Nov | M4: Dec | N4: Total | O4: % of revenue
A5: Revenue: mattresses | B5: =Assumptions!$K$5*Assumptions!B$36 -> 35429.94 | C5: =Assumptions!$K$5*Assumptions!C$36 -> 38155.32 | D5: =Assumptions!$K$5*Assumptions!D$36 -> 46331.46 | E5: =Assumptions!$K$5*Assumptions!E$36 -> 43606.08 | F5: =Assumptions!$K$5*Assumptions!F$36 -> 44532.709 | G5: =Assumptions!$K$5*Assumptions!G$36 -> 47258.089 | H5: =Assumptions!$K$5*Assumptions!H$36 -> 39954.071 | I5: =Assumptions!$K$5*Assumptions!I$36 -> 41807.329 | ... M5: =Assumptions!$K$5*Assumptions!M$36 -> 51782.22 | N5: =SUM(B5:M5) -> 545076 | O5: =IF($N$8=0,0,N5/$N$8) -> 0.42281879
A6: Revenue: slings | B6: =Assumptions!$K$6*Assumptions!B$36 -> 22776.39 | C6: =Assumptions!$K$6*Assumptions!C$36 -> 24528.42 | D6: =Assumptions!$K$6*Assumptions!D$36 -> 29784.51 | E6: =Assumptions!$K$6*Assumptions!E$36 -> 28032.48 | F6: =Assumptions!$K$6*Assumptions!F$36 -> 28628.17 | G6: =Assumptions!$K$6*Assumptions!G$36 -> 30380.2 | H6: =Assumptions!$K$6*Assumptions!H$36 -> 25684.76 | I6: =Assumptions!$K$6*Assumptions!I$36 -> 26876.14 | ... M6: =Assumptions!$K$6*Assumptions!M$36 -> 33288.57 | N6: =SUM(B6:M6) -> 350406 | O6: =IF($N$8=0,0,N6/$N$8) -> 0.27181208
A7: Revenue: braces | B7: =Assumptions!$K$7*Assumptions!B$36 -> 25588.29 | C7: =Assumptions!$K$7*Assumptions!C$36 -> 27556.62 | D7: =Assumptions!$K$7*Assumptions!D$36 -> 33461.61 | E7: =Assumptions!$K$7*Assumptions!E$36 -> 31493.28 | F7: =Assumptions!$K$7*Assumptions!F$36 -> 32162.512 | G7: =Assumptions!$K$7*Assumptions!G$36 -> 34130.842 | H7: =Assumptions!$K$7*Assumptions!H$36 -> 28855.718 | I7: =Assumptions!$K$7*Assumptions!I$36 -> 30194.182 | ... M7: =Assumptions!$K$7*Assumptions!M$36 -> 37398.27 | N7: =SUM(B7:M7) -> 393666 | O7: =IF($N$8=0,0,N7/$N$8) -> 0.30536913
A8: Total revenue | B8: =SUM(B5:B7) -> 83794.62 | C8: =SUM(C5:C7) -> 90240.36 | D8: =SUM(D5:D7) -> 109577.58 | E8: =SUM(E5:E7) -> 103131.84 | F8: =SUM(F5:F7) -> 105323.39 | G8: =SUM(G5:G7) -> 111769.13 | H8: =SUM(H5:H7) -> 94494.548 | I8: =SUM(I5:I7) -> 98877.652 | ... M8: =SUM(M5:M7) -> 122469.06 | N8: =SUM(B8:M8) -> 1289148 | O8: =IF($N$8=0,0,N8/$N$8) -> 1
A9: Materials | B9: =-Assumptions!$L$8*Assumptions!B$36 -> -38968.02 | C9: =-Assumptions!$L$8*Assumptions!C$36 -> -41965.56 | D9: =-Assumptions!$L$8*Assumptions!D$36 -> -50958.18 | E9: =-Assumptions!$L$8*Assumptions!E$36 -> -47960.64 | F9: =-Assumptions!$L$8*Assumptions!F$36 -> -48979.804 | G9: =-Assumptions!$L$8*Assumptions!G$36 -> -51977.344 | H9: =-Assumptions!$L$8*Assumptions!H$36 -> -43943.936 | I9: =-Assumptions!$L$8*Assumptions!I$36 -> -45982.264 | ... M9: =-Assumptions!$L$8*Assumptions!M$36 -> -56953.26 | N9: =SUM(B9:M9) -> -599508 | O9: =IF($N$8=0,0,N9/$N$8) -> -0.46504203
A10: Freight and export costs | B10: =-B8*Assumptions!$B$20 -> -3351.7848 | C10: =-C8*Assumptions!$B$20 -> -3609.6144 | D10: =-D8*Assumptions!$B$20 -> -4383.1032 | E10: =-E8*Assumptions!$B$20 -> -4125.2736 | F10: =-F8*Assumptions!$B$20 -> -4212.9357 | G10: =-G8*Assumptions!$B$20 -> -4470.7653 | H10: =-H8*Assumptions!$B$20 -> -3779.7819 | I10: =-I8*Assumptions!$B$20 -> -3955.1061 | ... M10: =-M8*Assumptions!$B$20 -> -4898.7624 | N10: =SUM(B10:M10) -> -51565.92 | O10: =IF($N$8=0,0,N10/$N$8) -> -0.04
A11: Sales commission | B11: =-B8*Assumptions!$B$21 -> -1675.8924 | C11: =-C8*Assumptions!$B$21 -> -1804.8072 | D11: =-D8*Assumptions!$B$21 -> -2191.5516 | E11: =-E8*Assumptions!$B$21 -> -2062.6368 | F11: =-F8*Assumptions!$B$21 -> -2106.4678 | G11: =-G8*Assumptions!$B$21 -> -2235.3826 | H11: =-H8*Assumptions!$B$21 -> -1889.891 | I11: =-I8*Assumptions!$B$21 -> -1977.553 | ... M11: =-M8*Assumptions!$B$21 -> -2449.3812 | N11: =SUM(B11:M11) -> -25782.96 | O11: =IF($N$8=0,0,N11/$N$8) -> -0.02
A12: Contribution | B12: =SUM(B8:B11) -> 39798.923 | C12: =SUM(C8:C11) -> 42860.378 | D12: =SUM(D8:D11) -> 52044.745 | E12: =SUM(E8:E11) -> 48983.29 | F12: =SUM(F8:F11) -> 50024.185 | G12: =SUM(G8:G11) -> 53085.64 | H12: =SUM(H8:H11) -> 44880.939 | I12: =SUM(I8:I11) -> 46962.729 | ... M12: =SUM(M8:M11) -> 58167.656 | N12: =SUM(B12:M12) -> 612291.12 | O12: =IF($N$8=0,0,N12/$N$8) -> 0.47495797
A13: Production wages | B13: =-(Assumptions!$B$11*(1+Assumptions!$B$12)+Assumptions!$B$13*Assumptions!$B$14*(1+Assumptions!$B$12))/12 -> -13426.667 | C13: =-(Assumptions!$B$11*(1+Assumptions!$B$12)+Assumptions!$B$13*Assumptions!$B$14*(1+Assumptions!$B$12))/12 -> -13426.667 | D13: =-(Assumptions!$B$11*(1+Assumptions!$B$12)+Assumptions!$B$13*Assumptions!$B$14*(1+Assumptions!$B$12))/12 -> -13426.667 | E13: =-(Assumptions!$B$11*(1+Assumptions!$B$12)+Assumptions!$B$13*Assumptions!$B$14*(1+Assumptions!$B$12))/12 -> -13426.667 | F13: =-(Assumptions!$B$11*(1+Assumptions!$B$12)+Assumptions!$B$13*Assumptions!$B$14*(1+Assumptions!$B$12))/12 -> -13426.667 | G13: =-(Assumptions!$B$11*(1+Assumptions!$B$12)+Assumptions!$B$13*Assumptions!$B$14*(1+Assumptions!$B$12))/12 -> -13426.667 | H13: =-(Assumptions!$B$11*(1+Assumptions!$B$12)+Assumptions!$B$13*Assumptions!$B$14*(1+Assumptions!$B$12))/12 -> -13426.667 | I13: =-(Assumptions!$B$11*(1+Assumptions!$B$12)+Assumptions!$B$13*Assumptions!$B$14*(1+Assumptions!$B$12))/12 -> -13426.667 | ... M13: =-(Assumptions!$B$11*(1+Assumptions!$B$12)+Assumptions!$B$13*Assumptions!$B$14*(1+Assumptions!$B$12))/12 -> -13426.667 | N13: =SUM(B13:M13) -> -161120 | O13: =IF($N$8=0,0,N13/$N$8) -> -0.12498177
A14: Factory overhead | B14: =-Assumptions!$B$15*(1+Assumptions!$B$17)/12 -> -10226.667 | C14: =-Assumptions!$B$15*(1+Assumptions!$B$17)/12 -> -10226.667 | D14: =-Assumptions!$B$15*(1+Assumptions!$B$17)/12 -> -10226.667 | E14: =-Assumptions!$B$15*(1+Assumptions!$B$17)/12 -> -10226.667 | F14: =-Assumptions!$B$15*(1+Assumptions!$B$17)/12 -> -10226.667 | G14: =-Assumptions!$B$15*(1+Assumptions!$B$17)/12 -> -10226.667 | H14: =-Assumptions!$B$15*(1+Assumptions!$B$17)/12 -> -10226.667 | I14: =-Assumptions!$B$15*(1+Assumptions!$B$17)/12 -> -10226.667 | ... M14: =-Assumptions!$B$15*(1+Assumptions!$B$17)/12 -> -10226.667 | N14: =SUM(B14:M14) -> -122720 | O14: =IF($N$8=0,0,N14/$N$8) -> -0.095194656
A15: Depreciation | B15: =-Assumptions!$B$16/12 -> -3791.6667 | C15: =-Assumptions!$B$16/12 -> -3791.6667 | D15: =-Assumptions!$B$16/12 -> -3791.6667 | E15: =-Assumptions!$B$16/12 -> -3791.6667 | F15: =-Assumptions!$B$16/12 -> -3791.6667 | G15: =-Assumptions!$B$16/12 -> -3791.6667 | H15: =-Assumptions!$B$16/12 -> -3791.6667 | I15: =-Assumptions!$B$16/12 -> -3791.6667 | ... M15: =-Assumptions!$B$16/12 -> -3791.6667 | N15: =SUM(B15:M15) -> -45500 | O15: =IF($N$8=0,0,N15/$N$8) -> -0.035294629
A16: Selling and admin | B16: =-Assumptions!$B$18*(1+Assumptions!$B$19)/12 -> -15080 | C16: =-Assumptions!$B$18*(1+Assumptions!$B$19)/12 -> -15080 | D16: =-Assumptions!$B$18*(1+Assumptions!$B$19)/12 -> -15080 | E16: =-Assumptions!$B$18*(1+Assumptions!$B$19)/12 -> -15080 | F16: =-Assumptions!$B$18*(1+Assumptions!$B$19)/12 -> -15080 | G16: =-Assumptions!$B$18*(1+Assumptions!$B$19)/12 -> -15080 | H16: =-Assumptions!$B$18*(1+Assumptions!$B$19)/12 -> -15080 | I16: =-Assumptions!$B$18*(1+Assumptions!$B$19)/12 -> -15080 | ... M16: =-Assumptions!$B$18*(1+Assumptions!$B$19)/12 -> -15080 | N16: =SUM(B16:M16) -> -180960 | O16: =IF($N$8=0,0,N16/$N$8) -> -0.14037178
A17: Operating profit | B17: =B12+SUM(B13:B16) -> -2726.0772 | C17: =C12+SUM(C13:C16) -> 335.3784 | D17: =D12+SUM(D13:D16) -> 9519.7452 | E17: =E12+SUM(E13:E16) -> 6458.2896 | F17: =F12+SUM(F13:F16) -> 7499.1845 | G17: =G12+SUM(G13:G16) -> 10560.64 | H17: =H12+SUM(H13:H16) -> 2355.9391 | I17: =I12+SUM(I13:I16) -> 4437.7289 | ... M17: =M12+SUM(M13:M16) -> 15642.656 | N17: =SUM(B17:M17) -> 101991.12 | O17: =IF($N$8=0,0,N17/$N$8) -> 0.079115137
A18: Interest | B18: =-Assumptions!$B$22/12 -> -1666.6667 | C18: =-Assumptions!$B$22/12 -> -1666.6667 | D18: =-Assumptions!$B$22/12 -> -1666.6667 | E18: =-Assumptions!$B$22/12 -> -1666.6667 | F18: =-Assumptions!$B$22/12 -> -1666.6667 | G18: =-Assumptions!$B$22/12 -> -1666.6667 | H18: =-Assumptions!$B$22/12 -> -1666.6667 | I18: =-Assumptions!$B$22/12 -> -1666.6667 | ... M18: =-Assumptions!$B$22/12 -> -1666.6667 | N18: =SUM(B18:M18) -> -20000 | O18: =IF($N$8=0,0,N18/$N$8) -> -0.015514123
A19: Profit before tax | B19: =B17+B18 -> -4392.7439 | C19: =C17+C18 -> -1331.2883 | D19: =D17+D18 -> 7853.0785 | E19: =E17+E18 -> 4791.6229 | F19: =F17+F18 -> 5832.5178 | G19: =G17+G18 -> 8893.9734 | H19: =H17+H18 -> 689.27243 | I19: =I17+I18 -> 2771.0622 | ... M19: =M17+M18 -> 13975.99 | N19: =SUM(B19:M19) -> 81991.12 | O19: =IF($N$8=0,0,N19/$N$8) -> 0.063601014
A20: Income tax | B20: =-Assumptions!$B$23*(MAX(0,SUM($B19:B19))-MAX(0,SUM($B19:B19)-B19)) -> 0 | C20: =-Assumptions!$B$23*(MAX(0,SUM($B19:C19))-MAX(0,SUM($B19:C19)-C19)) -> 0 | D20: =-Assumptions!$B$23*(MAX(0,SUM($B19:D19))-MAX(0,SUM($B19:D19)-D19)) -> -532.2616 | E20: =-Assumptions!$B$23*(MAX(0,SUM($B19:E19))-MAX(0,SUM($B19:E19)-E19)) -> -1197.9057 | F20: =-Assumptions!$B$23*(MAX(0,SUM($B19:F19))-MAX(0,SUM($B19:F19)-F19)) -> -1458.1295 | G20: =-Assumptions!$B$23*(MAX(0,SUM($B19:G19))-MAX(0,SUM($B19:G19)-G19)) -> -2223.4934 | H20: =-Assumptions!$B$23*(MAX(0,SUM($B19:H19))-MAX(0,SUM($B19:H19)-H19)) -> -172.31811 | I20: =-Assumptions!$B$23*(MAX(0,SUM($B19:I19))-MAX(0,SUM($B19:I19)-I19)) -> -692.76556 | ... M20: =-Assumptions!$B$23*(MAX(0,SUM($B19:M19))-MAX(0,SUM($B19:M19)-M19)) -> -3493.9974 | N20: =SUM(B20:M20) -> -20497.78 | O20: =IF($N$8=0,0,N20/$N$8) -> -0.015900254
A21: Net profit | B21: =B19+B20 -> -4392.7439 | C21: =C19+C20 -> -1331.2883 | D21: =D19+D20 -> 7320.8169 | E21: =E19+E20 -> 3593.7172 | F21: =F19+F20 -> 4374.3884 | G21: =G19+G20 -> 6670.4801 | H21: =H19+H20 -> 516.95432 | I21: =I19+I20 -> 2078.2967 | ... M21: =M19+M20 -> 10481.992 | N21: =SUM(B21:M21) -> 61493.34 | O21: =IF($N$8=0,0,N21/$N$8) -> 0.047700761
A23: Gross margin check: (revenue − materials − wages − overhead − depreciation) ÷ revenue | B23: =IF(N8=0,0,(N8+N9+N13+N14+N15)/N8) -> 0.27948692
A24: Contribution margin | B24: =IF(N8=0,0,N12/N8) -> 0.47495797
A25: Break-even sales | B25: =IF(B24<=0,0,-(N13+N14+N15+N16+N18)/B24) -> 1116519.8
A27: Income tax is worked out on year-to-date profit, so losses early in the year reduce tax later in the year. Real tax rules differ (Module 19).

Sheet Cash summary
A1: Budget cash summary for the year
A2: Working capital is estimated from the target days on the Assumptions sheet.
A3: Net profit | B3: ='Budget P&L'!N21 -> 61493.34
A4: Add back depreciation | B4: =Assumptions!$B$16 -> 45500
A5: Closing receivables (DSO × revenue ÷ 365) | B5: =Assumptions!$B$26*'Budget P&L'!N8/365 -> 229574.3
A6: Cash freed from receivables (negative = more cash tied up) | B6: =Assumptions!$B$29-B5 -> 425.69863
A7: Closing inventory (inventory days × materials, wages and factory overhead ÷ 365) | B7: =Assumptions!$B$27*-('Budget P&L'!N9+'Budget P&L'!N13+'Budget P&L'!N14)/365 -> 229912.49
A8: Cash freed from inventory (negative = more cash tied up) | B8: =Assumptions!$B$30-B7 -> 20087.507
A9: Closing payables (payable days × materials ÷ 365) | B9: =Assumptions!$B$28*-'Budget P&L'!N9/365 -> 103476.72
A10: Cash from more supplier credit | B10: =B9-Assumptions!$B$31 -> 8476.7233
A11: Cash from operations | B11: =B3+B4+B6+B8+B10 -> 135983.27
A12: Equipment purchases | B12: =-Assumptions!$B$24 -> -60000
A13: Loan repayments | B13: =-Assumptions!$B$25 -> -20000
A14: Net cash flow for the year | B14: =B11+B12+B13 -> 55983.269
A15: Opening cash | B15: =Assumptions!$B$32 -> 42000
A16: Closing cash (negative = extra borrowing needed) | B16: =B14+B15 -> 97983.269
