Workbook

Sheet How to use
A1: KPI dashboard
A2: The GM's Ledger course template. Example figures are for BraceWorks Medical, a fictional company: replace them with your own.
A4: What it's for
A5: A one-page monthly dashboard of 10 KPIs with targets, trend and red/amber/green status (Module 11).
A7: How to use it
A8: 1. Each month, fill the next column of the Monthly inputs sheet from the monthly pack.
A9: 2. Set a target, direction (higher or lower is better) and owner for each KPI on the Dashboard sheet.
A10: 3. Read the latest column and status. Ask each owner to explain anything amber or red.
A11: 4. Swap KPIs to suit your business, but keep the definitions written down and unchanged.
A13: Colour legend
A14: Blue text on yellow: an input. Type your own figures here.
A15: Black text: a formula. Don't overwrite these.
A16: Green text: a figure brought in from another sheet.

Sheet Dashboard
A1: Monthly KPI dashboard
A2: Status compares the latest month with the target. Off target = red, close = amber, on target = green.
A4: KPI | B4: Target | C4: Better if | D4: Owner | E4: Jan | F4: Feb | G4: Mar | H4: Apr | I4: May | J4: Jun | K4: Jul | L4: Aug | M4: Sep | N4: Oct | O4: Nov | P4: Dec | Q4: Latest | R4: Status
A5: Gross margin | B5: 0.3 | C5: Higher | D5: GM | E5: =IF('Monthly inputs'!B5="","",'Monthly inputs'!B6/'Monthly inputs'!B5) -> 0.27741935 | F5: =IF('Monthly inputs'!C5="","",'Monthly inputs'!C6/'Monthly inputs'!C5) -> 0.28043478 | G5: =IF('Monthly inputs'!D5="","",'Monthly inputs'!D6/'Monthly inputs'!D5) -> 0.26666667 | H5: =IF('Monthly inputs'!E5="","",'Monthly inputs'!E6/'Monthly inputs'!E5) | I5: =IF('Monthly inputs'!F5="","",'Monthly inputs'!F6/'Monthly inputs'!F5) | J5: =IF('Monthly inputs'!G5="","",'Monthly inputs'!G6/'Monthly inputs'!G5) | K5: =IF('Monthly inputs'!H5="","",'Monthly inputs'!H6/'Monthly inputs'!H5) | L5: =IF('Monthly inputs'!I5="","",'Monthly inputs'!I6/'Monthly inputs'!I5) | ... P5: =IF('Monthly inputs'!M5="","",'Monthly inputs'!M6/'Monthly inputs'!M5) | Q5: =IFERROR(LOOKUP(2,1/(E5:P5<>""),E5:P5),"") -> 0.26666667 | R5: =IF(Q5="","",IF(C5="Higher",IF(Q5>=B5,"On target",IF(Q5>=B5*0.95,"Close","Off target")),IF(Q5<=B5,"On target",IF(Q5<=B5*1.05,"Close","Off target")))) -> Off target
A6: EBITDA margin | B6: 0.11 | C6: Higher | D6: GM | E6: =IF('Monthly inputs'!B5="","",'Monthly inputs'!B7/'Monthly inputs'!B5) -> 0.095698925 | F6: =IF('Monthly inputs'!C5="","",'Monthly inputs'!C7/'Monthly inputs'!C5) -> 0.098913043 | G6: =IF('Monthly inputs'!D5="","",'Monthly inputs'!D7/'Monthly inputs'!D5) -> 0.096078431 | H6: =IF('Monthly inputs'!E5="","",'Monthly inputs'!E7/'Monthly inputs'!E5) | I6: =IF('Monthly inputs'!F5="","",'Monthly inputs'!F7/'Monthly inputs'!F5) | J6: =IF('Monthly inputs'!G5="","",'Monthly inputs'!G7/'Monthly inputs'!G5) | K6: =IF('Monthly inputs'!H5="","",'Monthly inputs'!H7/'Monthly inputs'!H5) | L6: =IF('Monthly inputs'!I5="","",'Monthly inputs'!I7/'Monthly inputs'!I5) | ... P6: =IF('Monthly inputs'!M5="","",'Monthly inputs'!M7/'Monthly inputs'!M5) | Q6: =IFERROR(LOOKUP(2,1/(E6:P6<>""),E6:P6),"") -> 0.096078431 | R6: =IF(Q6="","",IF(C6="Higher",IF(Q6>=B6,"On target",IF(Q6>=B6*0.95,"Close","Off target")),IF(Q6<=B6,"On target",IF(Q6<=B6*1.05,"Close","Off target")))) -> Off target
A7: Book-to-bill | B7: 1 | C7: Higher | D7: Sales | E7: =IF('Monthly inputs'!B5="","",'Monthly inputs'!B8/'Monthly inputs'!B5) -> 1.0322581 | F7: =IF('Monthly inputs'!C5="","",'Monthly inputs'!C8/'Monthly inputs'!C5) -> 1.0652174 | G7: =IF('Monthly inputs'!D5="","",'Monthly inputs'!D8/'Monthly inputs'!D5) -> 1.0392157 | H7: =IF('Monthly inputs'!E5="","",'Monthly inputs'!E8/'Monthly inputs'!E5) | I7: =IF('Monthly inputs'!F5="","",'Monthly inputs'!F8/'Monthly inputs'!F5) | J7: =IF('Monthly inputs'!G5="","",'Monthly inputs'!G8/'Monthly inputs'!G5) | K7: =IF('Monthly inputs'!H5="","",'Monthly inputs'!H8/'Monthly inputs'!H5) | L7: =IF('Monthly inputs'!I5="","",'Monthly inputs'!I8/'Monthly inputs'!I5) | ... P7: =IF('Monthly inputs'!M5="","",'Monthly inputs'!M8/'Monthly inputs'!M5) | Q7: =IFERROR(LOOKUP(2,1/(E7:P7<>""),E7:P7),"") -> 1.0392157 | R7: =IF(Q7="","",IF(C7="Higher",IF(Q7>=B7,"On target",IF(Q7>=B7*0.95,"Close","Off target")),IF(Q7<=B7,"On target",IF(Q7<=B7*1.05,"Close","Off target")))) -> On target
A8: Largest customer share of sales | B8: 0.2 | C8: Lower | D8: Sales | E8: =IF('Monthly inputs'!B5="","",'Monthly inputs'!B9/'Monthly inputs'!B5) -> 0.22580645 | F8: =IF('Monthly inputs'!C5="","",'Monthly inputs'!C9/'Monthly inputs'!C5) -> 0.2173913 | G8: =IF('Monthly inputs'!D5="","",'Monthly inputs'!D9/'Monthly inputs'!D5) -> 0.22058824 | H8: =IF('Monthly inputs'!E5="","",'Monthly inputs'!E9/'Monthly inputs'!E5) | I8: =IF('Monthly inputs'!F5="","",'Monthly inputs'!F9/'Monthly inputs'!F5) | J8: =IF('Monthly inputs'!G5="","",'Monthly inputs'!G9/'Monthly inputs'!G5) | K8: =IF('Monthly inputs'!H5="","",'Monthly inputs'!H9/'Monthly inputs'!H5) | L8: =IF('Monthly inputs'!I5="","",'Monthly inputs'!I9/'Monthly inputs'!I5) | ... P8: =IF('Monthly inputs'!M5="","",'Monthly inputs'!M9/'Monthly inputs'!M5) | Q8: =IFERROR(LOOKUP(2,1/(E8:P8<>""),E8:P8),"") -> 0.22058824 | R8: =IF(Q8="","",IF(C8="Higher",IF(Q8>=B8,"On target",IF(Q8>=B8*0.95,"Close","Off target")),IF(Q8<=B8,"On target",IF(Q8<=B8*1.05,"Close","Off target")))) -> Off target
A9: On time in full (OTIF) | B9: 0.95 | C9: Higher | D9: Production | E9: =IF('Monthly inputs'!B11="","",'Monthly inputs'!B10/'Monthly inputs'!B11) -> 0.86666667 | F9: =IF('Monthly inputs'!C11="","",'Monthly inputs'!C10/'Monthly inputs'!C11) -> 0.88709677 | G9: =IF('Monthly inputs'!D11="","",'Monthly inputs'!D10/'Monthly inputs'!D11) -> 0.89230769 | H9: =IF('Monthly inputs'!E11="","",'Monthly inputs'!E10/'Monthly inputs'!E11) | I9: =IF('Monthly inputs'!F11="","",'Monthly inputs'!F10/'Monthly inputs'!F11) | J9: =IF('Monthly inputs'!G11="","",'Monthly inputs'!G10/'Monthly inputs'!G11) | K9: =IF('Monthly inputs'!H11="","",'Monthly inputs'!H10/'Monthly inputs'!H11) | L9: =IF('Monthly inputs'!I11="","",'Monthly inputs'!I10/'Monthly inputs'!I11) | ... P9: =IF('Monthly inputs'!M11="","",'Monthly inputs'!M10/'Monthly inputs'!M11) | Q9: =IFERROR(LOOKUP(2,1/(E9:P9<>""),E9:P9),"") -> 0.89230769 | R9: =IF(Q9="","",IF(C9="Higher",IF(Q9>=B9,"On target",IF(Q9>=B9*0.95,"Close","Off target")),IF(Q9<=B9,"On target",IF(Q9<=B9*1.05,"Close","Off target")))) -> Off target
A10: Scrap rate | B10: 0.03 | C10: Lower | D10: Production | E10: =IF('Monthly inputs'!B13="","",'Monthly inputs'!B12/'Monthly inputs'!B13) -> 0.042222222 | F10: =IF('Monthly inputs'!C13="","",'Monthly inputs'!C12/'Monthly inputs'!C13) -> 0.040217391 | G10: =IF('Monthly inputs'!D13="","",'Monthly inputs'!D12/'Monthly inputs'!D13) -> 0.038016529 | H10: =IF('Monthly inputs'!E13="","",'Monthly inputs'!E12/'Monthly inputs'!E13) | I10: =IF('Monthly inputs'!F13="","",'Monthly inputs'!F12/'Monthly inputs'!F13) | J10: =IF('Monthly inputs'!G13="","",'Monthly inputs'!G12/'Monthly inputs'!G13) | K10: =IF('Monthly inputs'!H13="","",'Monthly inputs'!H12/'Monthly inputs'!H13) | L10: =IF('Monthly inputs'!I13="","",'Monthly inputs'!I12/'Monthly inputs'!I13) | ... P10: =IF('Monthly inputs'!M13="","",'Monthly inputs'!M12/'Monthly inputs'!M13) | Q10: =IFERROR(LOOKUP(2,1/(E10:P10<>""),E10:P10),"") -> 0.038016529 | R10: =IF(Q10="","",IF(C10="Higher",IF(Q10>=B10,"On target",IF(Q10>=B10*0.95,"Close","Off target")),IF(Q10<=B10,"On target",IF(Q10<=B10*1.05,"Close","Off target")))) -> Off target
A11: Days sales outstanding | B11: 60 | C11: Lower | D11: Finance | E11: =IF('Monthly inputs'!B5="","",'Monthly inputs'!B14/('Monthly inputs'!B5*12)*365) -> 73.261649 | F11: =IF('Monthly inputs'!C5="","",'Monthly inputs'!C14/('Monthly inputs'!C5*12)*365) -> 72.404891 | G11: =IF('Monthly inputs'!D5="","",'Monthly inputs'!D14/('Monthly inputs'!D5*12)*365) -> 63.815359 | H11: =IF('Monthly inputs'!E5="","",'Monthly inputs'!E14/('Monthly inputs'!E5*12)*365) | I11: =IF('Monthly inputs'!F5="","",'Monthly inputs'!F14/('Monthly inputs'!F5*12)*365) | J11: =IF('Monthly inputs'!G5="","",'Monthly inputs'!G14/('Monthly inputs'!G5*12)*365) | K11: =IF('Monthly inputs'!H5="","",'Monthly inputs'!H14/('Monthly inputs'!H5*12)*365) | L11: =IF('Monthly inputs'!I5="","",'Monthly inputs'!I14/('Monthly inputs'!I5*12)*365) | ... P11: =IF('Monthly inputs'!M5="","",'Monthly inputs'!M14/('Monthly inputs'!M5*12)*365) | Q11: =IFERROR(LOOKUP(2,1/(E11:P11<>""),E11:P11),"") -> 63.815359 | R11: =IF(Q11="","",IF(C11="Higher",IF(Q11>=B11,"On target",IF(Q11>=B11*0.95,"Close","Off target")),IF(Q11<=B11,"On target",IF(Q11<=B11*1.05,"Close","Off target")))) -> Off target
A12: Inventory days | B12: 85 | C12: Lower | D12: Production | E12: =IF('Monthly inputs'!B16="","",'Monthly inputs'!B15/('Monthly inputs'!B16*12)*365) -> 112.25198 | F12: =IF('Monthly inputs'!C16="","",'Monthly inputs'!C15/('Monthly inputs'!C16*12)*365) -> 110.73137 | G12: =IF('Monthly inputs'!D16="","",'Monthly inputs'!D15/('Monthly inputs'!D16*12)*365) -> 98.000223 | H12: =IF('Monthly inputs'!E16="","",'Monthly inputs'!E15/('Monthly inputs'!E16*12)*365) | I12: =IF('Monthly inputs'!F16="","",'Monthly inputs'!F15/('Monthly inputs'!F16*12)*365) | J12: =IF('Monthly inputs'!G16="","",'Monthly inputs'!G15/('Monthly inputs'!G16*12)*365) | K12: =IF('Monthly inputs'!H16="","",'Monthly inputs'!H15/('Monthly inputs'!H16*12)*365) | L12: =IF('Monthly inputs'!I16="","",'Monthly inputs'!I15/('Monthly inputs'!I16*12)*365) | ... P12: =IF('Monthly inputs'!M16="","",'Monthly inputs'!M15/('Monthly inputs'!M16*12)*365) | Q12: =IFERROR(LOOKUP(2,1/(E12:P12<>""),E12:P12),"") -> 98.000223 | R12: =IF(Q12="","",IF(C12="Higher",IF(Q12>=B12,"On target",IF(Q12>=B12*0.95,"Close","Off target")),IF(Q12<=B12,"On target",IF(Q12<=B12*1.05,"Close","Off target")))) -> Off target
A13: Lowest headroom, next 13 weeks | B13: 30000 | C13: Higher | D13: Finance | E13: =IF('Monthly inputs'!B19="","",'Monthly inputs'!B19) -> 61000 | F13: =IF('Monthly inputs'!C19="","",'Monthly inputs'!C19) -> 58000 | G13: =IF('Monthly inputs'!D19="","",'Monthly inputs'!D19) -> 56000 | H13: =IF('Monthly inputs'!E19="","",'Monthly inputs'!E19) | I13: =IF('Monthly inputs'!F19="","",'Monthly inputs'!F19) | J13: =IF('Monthly inputs'!G19="","",'Monthly inputs'!G19) | K13: =IF('Monthly inputs'!H19="","",'Monthly inputs'!H19) | L13: =IF('Monthly inputs'!I19="","",'Monthly inputs'!I19) | ... P13: =IF('Monthly inputs'!M19="","",'Monthly inputs'!M19) | Q13: =IFERROR(LOOKUP(2,1/(E13:P13<>""),E13:P13),"") -> 56000 | R13: =IF(Q13="","",IF(C13="Higher",IF(Q13>=B13,"On target",IF(Q13>=B13*0.95,"Close","Off target")),IF(Q13<=B13,"On target",IF(Q13<=B13*1.05,"Close","Off target")))) -> On target
A14: Net debt ÷ EBITDA | B14: 2 | C14: Lower | D14: GM | E14: =IF('Monthly inputs'!B18="","",'Monthly inputs'!B17/'Monthly inputs'!B18) -> 1.2781955 | F14: =IF('Monthly inputs'!C18="","",'Monthly inputs'!C17/'Monthly inputs'!C18) -> 1.2089552 | G14: =IF('Monthly inputs'!D18="","",'Monthly inputs'!D17/'Monthly inputs'!D18) -> 1.169697 | H14: =IF('Monthly inputs'!E18="","",'Monthly inputs'!E17/'Monthly inputs'!E18) | I14: =IF('Monthly inputs'!F18="","",'Monthly inputs'!F17/'Monthly inputs'!F18) | J14: =IF('Monthly inputs'!G18="","",'Monthly inputs'!G17/'Monthly inputs'!G18) | K14: =IF('Monthly inputs'!H18="","",'Monthly inputs'!H17/'Monthly inputs'!H18) | L14: =IF('Monthly inputs'!I18="","",'Monthly inputs'!I17/'Monthly inputs'!I18) | ... P14: =IF('Monthly inputs'!M18="","",'Monthly inputs'!M17/'Monthly inputs'!M18) | Q14: =IFERROR(LOOKUP(2,1/(E14:P14<>""),E14:P14),"") -> 1.169697 | R14: =IF(Q14="","",IF(C14="Higher",IF(Q14>=B14,"On target",IF(Q14>=B14*0.95,"Close","Off target")),IF(Q14<=B14,"On target",IF(Q14<=B14*1.05,"Close","Off target")))) -> On target
A16: Definitions: DSO and inventory days annualise the month (× 12). Write down any change of definition here, with the date.

Sheet Monthly inputs
A1: Monthly inputs for the dashboard
A2: US dollars unless stated. Fill one column per month; the dashboard calculates the KPIs.
A4: Input | B4: Jan | C4: Feb | D4: Mar | E4: Apr | F4: May | G4: Jun | H4: Jul | I4: Aug | J4: Sep | K4: Oct | L4: Nov | M4: Dec
A5: Revenue | B5: 93000 | C5: 92000 | D5: 102000
A6: Gross profit | B6: 25800 | C6: 25800 | D6: 27200
A7: EBITDA for the month | B7: 8900 | C7: 9100 | D7: 9800
A8: Orders received | B8: 96000 | C8: 98000 | D8: 106000
A9: Sales to largest customer | B9: 21000 | C9: 20000 | D9: 22500
A10: Orders delivered on time and in full (count) | B10: 52 | C10: 55 | D10: 58
A11: Orders delivered (count) | B11: 60 | C11: 62 | D11: 65
A12: Material scrapped ($) | B12: 1900 | C12: 1850 | D12: 1840
A13: Material issued to production ($) | B13: 45000 | C13: 46000 | D13: 48400
A14: Receivables at month-end | B14: 224000 | C14: 219000 | D14: 214000
A15: Inventory at month-end | B15: 248000 | C15: 241000 | D15: 241000
A16: Cost of goods sold for the month | B16: 67200 | C16: 66200 | D16: 74800
... A19: Lowest headroom in the next 13 weeks | B19: 61000 | C19: 58000 | D19: 56000
